bzComplexityAnalyzer/__init__.py
bzComplexityAnalyzer/bzComplexityAnalysis.py
bzcomplexityanalyzer-0.0.1.dist-info/METADATA
bzcomplexityanalyzer-0.0.1.dist-info/WHEEL
bzcomplexityanalyzer-0.0.1.dist-info/licenses/LICENSE
bzcomplexityanalyzer-0.0.1.dist-info/RECORD
