Metadata-Version: 2.1
Name: bzComplexityAnalyzer
Version: 0.0.1
Summary: Leverages the Burrows-Wheeler compression of BZip to estimate the complexity/information density of a sequence
Project-URL: Homepage, https://github.com/tecangenomics/bzComplexityAnalyzer
Project-URL: Bug Tracker, https://github.com/tecangenomics/bzComplexityAnalyzer/issues
Author-email: Michael Weinstein <michael.weinstein@tecan.com>
License:                     GNU GENERAL PUBLIC LICENSE
Classifier: Operating System :: OS Independent
Classifier: Programming Language :: Python :: 3
Requires-Python: >=3.7
